eumdac/__init__.py
eumdac/__version__.py
eumdac/cli.py
eumdac/cli_mtg_helpers.py
eumdac/collection.py
eumdac/common.py
eumdac/config.py
eumdac/customisation.py
eumdac/datastore.py
eumdac/datatailor.py
eumdac/download_app.py
eumdac/endpoints.ini
eumdac/errors.py
eumdac/fake.py
eumdac/futures.py
eumdac/job_id.py
eumdac/local_tailor.py
eumdac/lockfile.py
eumdac/logging.py
eumdac/order.py
eumdac/product.py
eumdac/py.typed
eumdac/request.py
eumdac/tailor_app.py
eumdac/tailor_models.py
eumdac/token.py
eumdac-3.0.0.dist-info/AUTHORS.txt
eumdac-3.0.0.dist-info/LICENSE.txt
eumdac-3.0.0.dist-info/LICENSE_APACHE_v2.txt
eumdac-3.0.0.dist-info/LICENSE_MIT.txt
eumdac-3.0.0.dist-info/METADATA
eumdac-3.0.0.dist-info/WHEEL
eumdac-3.0.0.dist-info/entry_points.txt
eumdac-3.0.0.dist-info/top_level.txt
eumdac-3.0.0.dist-info/RECORD
